parquool/__init__.py
parquool/agent.py
parquool/storage.py
parquool/util.py
parquool-0.0.10.dist-info/METADATA
parquool-0.0.10.dist-info/WHEEL
parquool-0.0.10.dist-info/top_level.txt
parquool-0.0.10.dist-info/RECORD
