Metadata-Version: 2.4
Name: parquool
Version: 0.0.10
Summary: Parquool - A Python Library for SQL like parquet query
Author-email: ppoak <ppoak@foxmail.com>
Project-URL: Homepage, https://github.com/ppoak/parquool
Keywords: quant,database,parquet,finance
Classifier: Programming Language :: Python :: 3
Classifier: License :: OSI Approved :: MIT License
Classifier: Operating System :: OS Independent
Requires-Python: >=3.10
Requires-Dist: dotenv>=0.8
Requires-Dist: duckdb>=1.0
Requires-Dist: joblib>=1.5
Requires-Dist: markdown>=3.0
Requires-Dist: numpy>=2.0
Requires-Dist: openai-agents>=0.2
Requires-Dist: pandas>=2.0
Requires-Dist: requests>=2.32
Requires-Dist: retry>=0.9
Provides-Extra: knowledge
Requires-Dist: chromadb>=1.1.0; extra == "knowledge"
Requires-Dist: pypdf>=6.1.0; extra == "knowledge"
Requires-Dist: python-docx>=1.2.0; extra == "knowledge"
Provides-Extra: websearch
Requires-Dist: serpapi>=0.1.0; extra == "websearch"
